{
  "main": {
    "id": "2f86700bfc0bd775",
    "type": "split",
    "children": [
      {
        "id": "003f496540f6e39b",
        "type": "tabs",
        "children": [
          {
            "id": "4bec7c0353d2518f",
            "type": "leaf",
            "state": {
              "type": "markdown",
              "state": {
                "file": "Logic/Conditional statements.md",
                "mode": "source",
                "source": false
              }
            }
          },
          {
            "id": "6b2c170a9ca22f05",
            "type": "leaf",
            "state": {
              "type": "markdown",
              "state": {
                "file": "Recursion and Induction/Sequence.md",
                "mode": "source",
                "source": false
              }
            }
          },
          {
            "id": "d383e977e6f06f66",
            "type": "leaf",
            "state": {
              "type": "markdown",
              "state": {
                "file": "Sets and Functions/Set-builder notation.md",
                "mode": "source",
                "source": false
              }
            }
          },
          {
            "id": "71a6e0237c83cc58",
            "type": "leaf",
            "state": {
              "type": "markdown",
              "state": {
                "file": "Recursion and Induction/Geometric sequence.md",
                "mode": "source",
                "source": false
              }
            }
          },
          {
            "id": "84a45363a8c996b4",
            "type": "leaf",
            "state": {
              "type": "markdown",
              "state": {
                "file": "Sets and Functions/Cardinality.md",
                "mode": "source",
                "source": false
              }
            }
          }
        ]
      }
    ],
    "direction": "vertical"
  },
  "left": {
    "id": "ce65857aaa5a3fa8",
    "type": "split",
    "children": [
      {
        "id": "a0505934223adf81",
        "type": "tabs",
        "children": [
          {
            "id": "648326dff836a8ba",
            "type": "leaf",
            "state": {
              "type": "file-explorer",
              "state": {
                "sortOrder": "alphabetical"
              }
            }
          },
          {
            "id": "727c59a6ce806dd8",
            "type": "leaf",
            "state": {
              "type": "search",
              "state": {
                "query": "counter",
                "matchingCase": false,
                "explainSearch": false,
                "collapseAll": false,
                "extraContext": false,
                "sortOrder": "alphabetical"
              }
            }
          },
          {
            "id": "979e2f25c0f22566",
            "type": "leaf",
            "state": {
              "type": "bookmarks",
              "state": {}
            }
          }
        ]
      }
    ],
    "direction": "horizontal",
    "width": 300
  },
  "right": {
    "id": "1a4a2bc639c7be39",
    "type": "split",
    "children": [
      {
        "id": "8bb504d0f7ffe543",
        "type": "tabs",
        "children": [
          {
            "id": "00391fd10cede494",
            "type": "leaf",
            "state": {
              "type": "outgoing-link",
              "state": {
                "file": "Logic/Conditional statements.md",
                "linksCollapsed": false,
                "unlinkedCollapsed": false
              }
            }
          },
          {
            "id": "982ef83193399f4d",
            "type": "leaf",
            "state": {
              "type": "tag",
              "state": {
                "sortOrder": "frequency",
                "useHierarchy": true
              }
            }
          },
          {
            "id": "e0b6f68a334f4dc3",
            "type": "leaf",
            "state": {
              "type": "outline",
              "state": {
                "file": "Logic/Conditional statements.md"
              }
            }
          },
          {
            "id": "b5aff26e395cb96a",
            "type": "leaf",
            "state": {
              "type": "git-view",
              "state": {}
            }
          },
          {
            "id": "20e7e6d27e4c4c44",
            "type": "leaf",
            "state": {
              "type": "backlink",
              "state": {
                "file": "Logic/Conditional statements.md",
                "collapseAll": false,
                "extraContext": false,
                "sortOrder": "alphabetical",
                "showSearch": false,
                "searchQuery": "",
                "backlinkCollapsed": false,
                "unlinkedCollapsed": true
              }
            }
          }
        ]
      }
    ],
    "direction": "horizontal",
    "width": 300
  },
  "left-ribbon": {
    "hiddenItems": {
      "switcher:Open quick switcher": false,
      "graph:Open graph view": false,
      "canvas:Create new canvas": false,
      "daily-notes:Open today's daily note": false,
      "templates:Insert template": false,
      "command-palette:Open command palette": false,
      "publish:Publish changes...": false,
      "table-editor-obsidian:Advanced Tables Toolbar": false,
      "custom-sort:Toggle custom sorting": false,
      "templater-obsidian:Templater": false
    }
  },
  "active": "4bec7c0353d2518f",
  "lastOpenFiles": [
    "Sets and Functions/Power set.md",
    "Sets and Functions/Cardinality.md",
    "Recursion and Induction/Arithmetic sequence.md",
    "Recursion and Induction/Geometric sequence.md",
    "recursively.md",
    "Untitled 2.md",
    "Recursion and Induction/Sequence.md",
    "Sets and Functions/Universal set.md",
    "Assets/Images/venn-diagram-of-universal-set-1627631133.png.sb-0a91eb07-IVCx0D",
    "Assets/Images/venn-diagram-of-universal-set-1627631133.png",
    "Sets and Functions/Roster notation.md",
    "Sets and Functions/Set-builder notation.md",
    "Sets and Functions/Set.md",
    "Untitled.md",
    "Recursion and Induction/Recurrence relation.md",
    "Recursion and Induction/Closed formula.md",
    "Untitled 1.md",
    "Assets/Images/triangular-visual.png",
    "Sets and Functions/Subset.md",
    "Sets and Functions/Codomain.md",
    "Assets/Images/simple-function-diagram.png",
    "Sets and Functions/Function.md",
    "Assets/Images/Pasted image 20230718094622.png",
    "Sets and Functions/Range.md",
    "Pasted image 20230828102253.png",
    "Logic/Negation.md",
    "Logic/Inverse.md",
    "Sets and Functions/Empty set.md",
    "Sets and Functions/Domain.md",
    "Recursion and Induction/Fibonacci sequence.md",
    "README.md",
    "Counting/Weight of a bitstring.md",
    "Assets/Images/graphview.jpg",
    "binary-division.jpg",
    "Untitled.jpg",
    "Assets/Images",
    "Assets/Templates",
    "Counting",
    "Recursion and Induction",
    "Sets and Functions",
    "Computer Arithmetic",
    "Assets/Images/mth225-logo.png",
    "mth225-logo.png",
    "Assets",
    "untitled folder",
    "Test canvas.canvas",
    "Logic"
  ]
}